{
  "categories": [
    {
      "id": 1,
      "name": "Rings",
      "slug": "rings"
    },
    {
      "id": 2,
      "name": "Necklaces",
      "slug": "necklaces"
    },
    {
      "id": 3,
      "name": "Earrings",
      "slug": "earrings"
    },
    {
      "id": 4,
      "name": "Bracelets",
      "slug": "bracelets"
    }
  ],
  "products": [
    {
      "id": 1,
      "name": "Pink Diamond Ring",
      "categoryId": 1,
      "price": 500,
      "currency": "USD",
      "discountPercent": 20,
      "rating": 4.8,
      "reviewsCount": 124,
      "material": "925 Sterling Silver",
      "stone": "Round Cut Cubic Zircon",
      "weight": "0.4 ct",
      "description": "Round cut cubic zircon stones set in sterling silver with rhodium plating. Perfect for special occasions.",
      "images": [
        "/images/products/pink-diamond-1.png",
        "/images/products/pink-diamond-2.png"
      ],
      "isFeatured": true,
      "inStock": true
    },
    {
      "id": 2,
      "name": "Blue Crystal Ring",
      "categoryId": 1,
      "price": 420,
      "currency": "USD",
      "discountPercent": 0,
      "rating": 4.5,
      "reviewsCount": 89,
      "material": "White Gold",
      "stone": "Blue Crystal",
      "weight": "0.35 ct",
      "description": "Elegant blue crystal ring crafted with precision and premium materials.",
      "images": [
        "/images/products/blue-ring-1.png"
      ],
      "isFeatured": false,
      "inStock": true
    },
    {
      "id": 3,
      "name": "Diamond Necklace",
      "categoryId": 2,
      "price": 780,
      "currency": "USD",
      "discountPercent": 10,
      "rating": 2,
      "reviewsCount": 201,
      "material": "18K Gold",
      "stone": "Diamond",
      "weight": "0.6 ct",
      "description": "Minimalist diamond necklace designed for everyday elegance.",
      "images": [
        "/images/products/diamond-necklace-1.png"
      ],
      "isFeatured": true,
      "inStock": true
    },
    {
      "id": 4,
      "name": "Rose Gold Earrings",
      "categoryId": 3,
      "price": 260,
      "currency": "USD",
      "discountPercent": 0,
      "rating": 4.3,
      "reviewsCount": 56,
      "material": "Rose Gold",
      "stone": "Zircon",
      "weight": "0.25 ct",
      "description": "Lightweight rose gold earrings with subtle zircon sparkle.",
      "images": [
        "/images/products/rose-earrings-1.png"
      ],
      "isFeatured": false,
      "inStock": true
    }
  ],
  "carts": [
    {
      "id": 1,
      "userId": 1,
      "items": [
        {
          "productId": 1,
          "quantity": 1,
          "price": 500
        },
        {
          "productId": 2,
          "quantity": 1,
          "price": 420
        }
      ],
      "subtotal": 920,
      "deliveryFee": 50,
      "total": 970,
      "updatedAt": "2025-01-12T10:30:00Z"
    },
    {
      "items": [],
      "subtotal": 0,
      "deliveryFee": 0,
      "total": 0,
      "id": 2
    },
    {
      "items": [],
      "subtotal": 0,
      "deliveryFee": 0,
      "total": 0,
      "id": 3
    },
    {
      "items": [],
      "subtotal": 0,
      "deliveryFee": 0,
      "total": 0,
      "id": 4
    },
    {
      "items": [],
      "subtotal": 0,
      "deliveryFee": 0,
      "total": 0,
      "id": 5
    },
    {
      "items": [],
      "subtotal": 0,
      "deliveryFee": 0,
      "total": 0,
      "id": 6
    },
    {
      "items": [],
      "subtotal": 0,
      "deliveryFee": 0,
      "total": 0,
      "id": 7
    },
    {
      "items": [],
      "subtotal": 0,
      "deliveryFee": 0,
      "total": 0,
      "id": 8
    },
    {
      "items": [],
      "subtotal": 0,
      "deliveryFee": 0,
      "total": 0,
      "id": 9
    },
    {
      "items": [],
      "subtotal": 0,
      "deliveryFee": 0,
      "total": 0,
      "id": 10
    },
    {
      "items": [],
      "subtotal": 0,
      "deliveryFee": 0,
      "total": 0,
      "id": 11
    },
    {
      "items": [],
      "subtotal": 0,
      "deliveryFee": 0,
      "total": 0,
      "id": 12
    },
    {
      "items": [],
      "subtotal": 0,
      "deliveryFee": 0,
      "total": 0,
      "id": 13
    },
    {
      "items": [],
      "subtotal": 0,
      "deliveryFee": 0,
      "total": 0,
      "id": 14
    },
    {
      "items": [],
      "subtotal": 0,
      "deliveryFee": 0,
      "total": 0,
      "id": 15
    },
    {
      "items": [],
      "subtotal": 0,
      "deliveryFee": 0,
      "total": 0,
      "id": 16
    },
    {
      "items": [],
      "subtotal": 0,
      "deliveryFee": 0,
      "total": 0,
      "id": 17
    },
    {
      "items": [],
      "subtotal": 0,
      "deliveryFee": 0,
      "total": 0,
      "id": 18
    },
    {
      "items": [],
      "subtotal": 0,
      "deliveryFee": 0,
      "total": 0,
      "id": 19
    },
    {
      "items": [],
      "subtotal": 0,
      "deliveryFee": 0,
      "total": 0,
      "id": 20
    },
    {
      "items": [],
      "subtotal": 0,
      "deliveryFee": 0,
      "total": 0,
      "id": 21
    },
    {
      "items": [],
      "subtotal": 0,
      "deliveryFee": 0,
      "total": 0,
      "id": 22
    },
    {
      "items": [],
      "subtotal": 0,
      "deliveryFee": 0,
      "total": 0,
      "id": 23
    },
    {
      "items": [],
      "subtotal": 0,
      "deliveryFee": 0,
      "total": 0,
      "id": 24
    },
    {
      "items": [],
      "subtotal": 0,
      "deliveryFee": 0,
      "total": 0,
      "id": 25
    },
    {
      "items": [],
      "subtotal": 0,
      "deliveryFee": 0,
      "total": 0,
      "id": 26
    },
    {
      "items": [],
      "subtotal": 0,
      "deliveryFee": 0,
      "total": 0,
      "id": 27
    },
    {
      "items": [],
      "subtotal": 0,
      "deliveryFee": 0,
      "total": 0,
      "id": 28
    },
    {
      "items": [],
      "subtotal": 0,
      "deliveryFee": 0,
      "total": 0,
      "id": 29
    },
    {
      "items": [],
      "subtotal": 0,
      "deliveryFee": 0,
      "total": 0,
      "id": 30
    },
    {
      "items": [],
      "subtotal": 0,
      "deliveryFee": 0,
      "total": 0,
      "id": 31
    },
    {
      "items": [],
      "subtotal": 0,
      "deliveryFee": 0,
      "total": 0,
      "id": 32
    },
    {
      "items": [],
      "subtotal": 0,
      "deliveryFee": 0,
      "total": 0,
      "id": 33
    },
    {
      "items": [],
      "subtotal": 0,
      "deliveryFee": 0,
      "total": 0,
      "id": 34
    },
    {
      "items": [],
      "subtotal": 0,
      "deliveryFee": 0,
      "total": 0,
      "id": 35
    },
    {
      "items": [],
      "subtotal": 0,
      "deliveryFee": 0,
      "total": 0,
      "id": 36
    },
    {
      "items": [],
      "subtotal": 0,
      "deliveryFee": 0,
      "total": 0,
      "id": 37
    },
    {
      "items": [],
      "subtotal": 0,
      "deliveryFee": 0,
      "total": 0,
      "id": 38
    },
    {
      "items": [],
      "subtotal": 0,
      "deliveryFee": 0,
      "total": 0,
      "id": 39
    },
    {
      "items": [],
      "subtotal": 0,
      "deliveryFee": 0,
      "total": 0,
      "id": 40
    },
    {
      "items": [],
      "subtotal": 0,
      "deliveryFee": 0,
      "total": 0,
      "id": 41
    },
    {
      "items": [],
      "subtotal": 0,
      "deliveryFee": 0,
      "total": 0,
      "id": 42
    },
    {
      "items": [],
      "subtotal": 0,
      "deliveryFee": 0,
      "total": 0,
      "id": 43
    },
    {
      "items": [],
      "subtotal": 0,
      "deliveryFee": 0,
      "total": 0,
      "id": 44
    },
    {
      "items": [],
      "subtotal": 0,
      "deliveryFee": 0,
      "total": 0,
      "id": 45
    },
    {
      "items": [],
      "subtotal": 0,
      "deliveryFee": 0,
      "total": 0,
      "id": 46
    },
    {
      "items": [],
      "subtotal": 0,
      "deliveryFee": 0,
      "total": 0,
      "id": 47
    },
    {
      "items": [],
      "subtotal": 0,
      "deliveryFee": 0,
      "total": 0,
      "id": 48
    },
    {
      "items": [],
      "subtotal": 0,
      "deliveryFee": 0,
      "total": 0,
      "id": 49
    },
    {
      "items": [],
      "subtotal": 0,
      "deliveryFee": 0,
      "total": 0,
      "id": 50
    },
    {
      "items": [],
      "subtotal": 0,
      "deliveryFee": 0,
      "total": 0,
      "id": 51
    },
    {
      "items": [],
      "subtotal": 0,
      "deliveryFee": 0,
      "total": 0,
      "id": 52
    }
  ],
  "orders": [
    {
      "id": 1,
      "userId": 1,
      "items": [
        {
          "productId": 1,
          "name": "Pink Diamond Ring",
          "quantity": 2,
          "price": 500
        }
      ],
      "deliveryAddress": {
        "fullName": "Robert Fox",
        "street": "Imran Road",
        "city": "Lahore",
        "country": "Pakistan",
        "postalCode": "54000"
      },
      "payment": {
        "method": "Visa",
        "last4": "3947"
      },
      "subtotal": 1000,
      "deliveryFee": 50,
      "total": 1050,
      "status": "paid",
      "createdAt": "2025-01-11T18:15:00Z"
    }
  ]
}